jxlang/__init__.py
jxlang/exceptions.py
jxlang/interpreter.py
jxlang/lexer.py
jxlang/parser.py
jxlang/repl.py
jxlang/tokens.py
jxlang-0.3.126.dist-info/LICENSE
jxlang-0.3.126.dist-info/METADATA
jxlang-0.3.126.dist-info/WHEEL
jxlang-0.3.126.dist-info/entry_points.txt
jxlang-0.3.126.dist-info/top_level.txt
jxlang-0.3.126.dist-info/RECORD
