Metadata-Version: 2.1
Name: jxlang
Version: 0.3.126
Summary: A custom programming language jxlang
Author-email: AndyKingXi <appleking0@icloud.com>
License: Apache 2.0
Project-URL: Homepage, https://gitee.com/JXX_CODE/jx-lang
Keywords: programming-language,repl,interpreter
Classifier: Programming Language :: Python :: 3
Classifier: Operating System :: OS Independent
Requires-Python: >=3.7
License-File: LICENSE
